{
  "name": "logger",
  "version": "1.0.0",
  "godot_version": "4.7",
  "description_pt": "Behavior logger para Godot 4.7.",
  "description_en": "logger behavior for Godot 4.7.",
  "synonyms": {
    "pt": [
      "logger"
    ],
    "en": [
      "logger"
    ]
  },
  "parameters": [],
  "signals": [],
  "genres": [
    "generic"
  ],
  "conflicts": [],
  "tags": [],
  "combina_bem": [
    "hurtbox",
    "hitbox",
    "health",
    "particle_impact",
    "sfx_player",
    "screen_shake",
    "object_pool",
    "tween_player"
  ],
  "custo": "leve",
  "verbo_pt": "registrar_log",
  "verbo_en": "log",
  "nivel": "basico"
}
