{
  "name": "enemy_patrol",
  "description_pt": "Patrulha entre waypoints: move o CharacterBody2D pai por uma rota de pontos, espera em cada um, faz loop ou ping-pong. Integra com state_machine para estados patrol/idle.",
  "description_en": "Patrol between waypoints: moves the parent CharacterBody2D along a route, waits at each point, loops or ping-pongs. Integrates with state_machine for patrol/idle states.",
  "synonyms": {
    "pt": [
      "patrulha",
      "rota",
      "ronda",
      "vigia",
      "guardar",
      "caminho",
      "percurso"
    ],
    "en": [
      "patrol",
      "route",
      "guard",
      "walk",
      "waypoint",
      "path",
      "march"
    ]
  },
  "parameters": [
    {
      "name": "waypoints",
      "type": "PackedVector2Array",
      "description_pt": "Lista de posições globais (mundo) para patrulhar.",
      "default": []
    },
    {
      "name": "speed",
      "type": "float",
      "description_pt": "Velocidade de movimento entre waypoints (px/s).",
      "range": {
        "min": 10.0,
        "max": 2000.0
      },
      "default": 100.0,
      "unit": "px/s"
    },
    {
      "name": "wait_time",
      "type": "float",
      "description_pt": "Tempo de espera em cada waypoint (s).",
      "range": {
        "min": 0.0,
        "max": 60.0
      },
      "default": 1.0,
      "unit": "s"
    },
    {
      "name": "loop",
      "type": "bool",
      "description_pt": "Se true, após o último waypoint volta ao primeiro e recomeça.",
      "default": true
    },
    {
      "name": "ping_pong",
      "type": "bool",
      "description_pt": "Se true, inverte direção ao chegar nas pontas (ida e volta). Tem precedência sobre loop.",
      "default": false
    }
  ],
  "signals": [
    {
      "name": "waypoint_reached",
      "description_pt": "Emitido ao chegar em um waypoint.",
      "params": [
        {
          "name": "index",
          "type": "int"
        }
      ]
    },
    {
      "name": "patrol_complete",
      "description_pt": "Emitido ao completar a rota (sem loop nem ping_pong).",
      "params": []
    }
  ],
  "dependencies": [
    "state_machine"
  ],
  "genres": [
    "platformer",
    "topdown_shooter",
    "roguelike",
    "metroidvania",
    "stealth",
    "generic"
  ],
  "conflicts": [],
  "version": "1.0.0",
  "godot_version": "4.7",
  "tags": [
    "ia",
    "patrulha",
    "movimento",
    "waypoint",
    "npc",
    "inimigo"
  ],
  "combina_bem": [
    "state_machine",
    "health",
    "hurtbox",
    "flee",
    "hitbox",
    "status_effect",
    "save_load",
    "line_of_sight"
  ],
  "custo": "medio",
  "verbo_pt": "patrulhar",
  "verbo_en": "patrol",
  "nivel": "intermediario",
  "preview_gif": "preview.gif",
  "preview_type": "abstract"
}
